FuckItPy-0.0.2.data/scripts/fuckitpy.py
fuckitpy/__init__.py
fuckitpy/fuckitpy.py
FuckItPy-0.0.2.dist-info/LICENSE
FuckItPy-0.0.2.dist-info/METADATA
FuckItPy-0.0.2.dist-info/WHEEL
FuckItPy-0.0.2.dist-info/entry_points.txt
FuckItPy-0.0.2.dist-info/top_level.txt
FuckItPy-0.0.2.dist-info/RECORD
