Metadata-Version: 2.1
Name: FuckItPy
Version: 0.0.2
Summary: Best way to eliminate python errors!
Home-page: https://github.com/BachelorForever/FuckitPy
Author: BachelorForever
License: UNKNOWN
Project-URL: Bug Tracker, https://github.com/BachelorForever/FuckitPy/issues
Platform: UNKNOWN
Classifier: Programming Language :: Python :: 3
Classifier: Operating System :: OS Independent
Requires-Python: >=3.6
License-File: LICENSE
